{
  "routes": [
    {
      "method": "GET",
      "path": "/advertises",
      "handler": "advertise.find",
      "config": {
        "policies": []
      }
    },
    {
      "method": "GET",
      "path": "/advertises/count",
      "handler": "advertise.count",
      "config": {
        "policies": []
      }
    },
    {
      "method": "GET",
      "path": "/advertises/:id",
      "handler": "advertise.findOne",
      "config": {
        "policies": []
      }
    },
    {
      "method": "POST",
      "path": "/advertises",
      "handler": "advertise.create",
      "config": {
        "policies": []
      }
    },
    {
      "method": "PUT",
      "path": "/advertises/:id",
      "handler": "advertise.update",
      "config": {
        "policies": []
      }
    },
    {
      "method": "DELETE",
      "path": "/advertises/:id",
      "handler": "advertise.delete",
      "config": {
        "policies": []
      }
    }
  ]
}
